{
  "pokemon": [
    {
      "name": "Bulbasaur",
      "id": 1,
      "type": [
        "grass",
        "poison"
      ],
      "bstats": {
        "hp": 45,
        "att": 49,
        "def": 49,
        "satt": 65,
        "sdef": 65,
        "spd": 45
      },
      "pnum": "001"
    },
    {
      "name": "Yvysaur",
      "id": 2,
      "type": [
        "grass",
        "poison"
      ],
      "bstats": {
        "hp": 60,
        "att": 62,
        "def": 63,
        "satt": 80,
        "sdef": 80,
        "spd": 60
      },
      "pnum": "002"
    },
    {
      "name": "Venusaur",
      "id": 3,
      "type": [
        "grass",
        "poison"
      ],
      "bstats": {
        "hp": 80,
        "att": 82,
        "def": 83,
        "satt": 100,
        "sdef": 100,
        "spd": 80
      },
      "pnum": "003"
    },
    {
      "name": "Venusaur",
      "id": 3,
      "type": [
        "grass",
        "poison"
      ],
      "bstats": {
        "hp": 80,
        "att": 82,
        "def": 83,
        "satt": 100,
        "sdef": 100,
        "spd": 80
      },
      "pnum": "003"
    }
  ]
}